strong_opx/__init__.py
strong_opx/compat.py
strong_opx/exceptions.py
strong_opx/helm.py
strong_opx/vault.py
strong_opx/ansible/__init__.py
strong_opx/ansible/filter_plugins/__init__.py
strong_opx/ansible/filter_plugins/ec2.py
strong_opx/codegen/__init__.py
strong_opx/codegen/generator.py
strong_opx/codegen/project_generator.py
strong_opx/codegen/questions.py
strong_opx/codegen/generators/__init__.py
strong_opx/codegen/generators/environment.py
strong_opx/config/__init__.py
strong_opx/config/base.py
strong_opx/config/hierarchical.py
strong_opx/config/opx.py
strong_opx/hcl/__init__.py
strong_opx/hcl/extractor.py
strong_opx/hcl/packer.py
strong_opx/hcl/runner.py
strong_opx/hcl/terraform.py
strong_opx/management/__init__.py
strong_opx/management/command.py
strong_opx/management/entrypoint.py
strong_opx/management/utils.py
strong_opx/management/commands/__init__.py
strong_opx/management/commands/aws_configure.py
strong_opx/management/commands/aws_mfa.py
strong_opx/management/commands/compute.py
strong_opx/management/commands/config.py
strong_opx/management/commands/deploy.py
strong_opx/management/commands/docker_build.py
strong_opx/management/commands/generate.py
strong_opx/management/commands/helm.py
strong_opx/management/commands/k8s.py
strong_opx/management/commands/kubectl.py
strong_opx/management/commands/packer.py
strong_opx/management/commands/playbook.py
strong_opx/management/commands/project.py
strong_opx/management/commands/run.py
strong_opx/management/commands/scp.py
strong_opx/management/commands/ssh.py
strong_opx/management/commands/terraform.py
strong_opx/management/commands/vars.py
strong_opx/platforms/__init__.py
strong_opx/platforms/base.py
strong_opx/platforms/generic.py
strong_opx/platforms/kubernetes.py
strong_opx/platforms/deployments/__init__.py
strong_opx/platforms/deployments/base.py
strong_opx/platforms/deployments/kubectl.py
strong_opx/platforms/plugins/__init__.py
strong_opx/platforms/plugins/kubernetes_dashboard.py
strong_opx-1.4.0.dist-info/licenses/LICENSE
strong_opx-1.4.0.dist-info/METADATA
strong_opx-1.4.0.dist-info/WHEEL
strong_opx-1.4.0.dist-info/entry_points.txt
strong_opx-1.4.0.dist-info/top_level.txt
strong_opx-1.4.0.dist-info/RECORD
