Metadata-Version: 2.4
Name: strong-opx
Version: 1.4.0
Summary: Tools for deploying and managing infrastructure
Author-email: Adnan Umer <u.adnan@outlook.com>
License: MIT License
Project-URL: Homepage, https://github.com/strongio/strong-opx
Project-URL: Issues, https://github.com/strongio/strong-opx/issues
Classifier: Development Status :: 5 - Production/Stable
Classifier: Intended Audience :: Developers
Classifier: Programming Language :: Python :: 3
Classifier: Programming Language :: Python :: 3.9
Classifier: Programming Language :: Python :: 3.10
Classifier: Programming Language :: Python :: 3.11
Classifier: Programming Language :: Python :: 3.12
Requires-Python: >=3.9
License-File: LICENSE
Requires-Dist: Jinja2
Requires-Dist: PyYAML
Requires-Dist: ansible
Requires-Dist: colorama
Requires-Dist: filelock
Requires-Dist: prompt-toolkit>=3.0.39
Requires-Dist: pydantic>=2.9
Requires-Dist: tabulate
Provides-Extra: dev
Requires-Dist: moto>=5; extra == "dev"
Requires-Dist: isort; extra == "dev"
Requires-Dist: pytest-tldr; extra == "dev"
Requires-Dist: pytest; extra == "dev"
Requires-Dist: toml; extra == "dev"
Requires-Dist: black; extra == "dev"
Requires-Dist: coverage; extra == "dev"
Requires-Dist: parameterized; extra == "dev"
Requires-Dist: astunparse; extra == "dev"
Provides-Extra: aws
Requires-Dist: awscli; extra == "aws"
Requires-Dist: boto3; extra == "aws"
Provides-Extra: azure
Requires-Dist: azure-identity; extra == "azure"
Requires-Dist: azure-keyvault-secrets; extra == "azure"
Provides-Extra: gcloud
Requires-Dist: google-cloud-artifact-registry; extra == "gcloud"
Provides-Extra: standard
Requires-Dist: strong-opx[aws,azure,gcloud]; extra == "standard"
Dynamic: license-file
